co2_reading_plugin/__init__.py
co2_reading_plugin/additional_config.ini
co2_reading_plugin/additional_sql.sql
co2_reading_plugin/exportable_datasets/co2_readings.yaml
co2_reading_plugin/ui/contrib/charts/co2_readings.yaml
co2_reading_plugin/ui/contrib/jobs/co2_reading.yaml
co2_reading_plugin-0.3.0.dist-info/licenses/LICENSE.txt
co2_reading_plugin-0.3.0.dist-info/METADATA
co2_reading_plugin-0.3.0.dist-info/WHEEL
co2_reading_plugin-0.3.0.dist-info/entry_points.txt
co2_reading_plugin-0.3.0.dist-info/top_level.txt
co2_reading_plugin-0.3.0.dist-info/RECORD
