Metadata-Version: 2.4
Name: co2-reading-plugin
Version: 0.3.0
Summary: Return a CO₂ reading every interval from an Adafruit CO₂ sensors SCD30, SCD40 or SCD41.
Home-page: https://github.com/Pioreactor/co2_reading_plugin
Author: Kelly Tran, Cameron Davidson-Pilon
Author-email: cam@pioreactor.com
License: MIT
License-File: LICENSE.txt
Requires-Dist: adafruit-circuitpython-scd30
Requires-Dist: adafruit-circuitpython-scd4x
Dynamic: author
Dynamic: author-email
Dynamic: description
Dynamic: description-content-type
Dynamic: home-page
Dynamic: license
Dynamic: license-file
Dynamic: requires-dist
Dynamic: summary
